Multi Cycle/aludec.v

module aludec(input   [5:0] funct,
              input   [1:0] aluop,
              output  reg [3:0] alucontrol);

  always @ (*) begin
    case(aluop)
      2'b00: alucontrol <= 4'b0000;  // add
      2'b01: alucontrol <= 4'b0010;  // sub
      2'b11: alucontrol <= 4'b0101;  // or
      default: case(funct)          // RTYPE
          6'b100000: alucontrol <= 4'b0000; // ADD
          6'b100010: alucontrol <= 4'b0010; // SUB
          6'b100100: alucontrol <= 4'b0100; // AND
          6'b100101: alucontrol <= 4'b0101; // OR
          6'b100110: alucontrol <= 4'b0110; // XOR
          6'b100111: alucontrol <= 4'b0111; // NOR
          6'b101010: alucontrol <= 4'b1010; // SLT
          default:   alucontrol <= 4'bxxxx; // ???
        endcase
    endcase
  end
  // Remember that you may also reuse any code from previous labs.

endmodule

Multi Cycle/maindec.v

module maindec(input         clk, reset, 
               input   [5:0] op, 
               output        pcwrite, memwrite, irwrite, regwrite,
               output        alusrca, branch, iord, memtoreg, regdst,
               output  [1:0] alusrcb, pcsrc,
               output  [1:0] aluop);

  parameter   FETCH   = 4'b0000; // State 0
  parameter   DECODE  = 4'b0001; // State 1
  parameter   MEMADR  = 4'b0010;	// State 2
  parameter   MEMRD   = 4'b0011;	// State 3
  parameter   MEMWB   = 4'b0100;	// State 4
  parameter   MEMWR   = 4'b0101;	// State 5
  parameter   RTYPEEX = 4'b0110;	// State 6
  parameter   RTYPEWB = 4'b0111;	// State 7
  parameter   BEQEX   = 4'b1000;	// State 8
  parameter   ADDIEX  = 4'b1001;	// State 9
  parameter   ADDIWB  = 4'b1010;	// state 10
  parameter   JEX     = 4'b1011;	// State 11

  parameter   LW      = 6'b100011;	// Opcode for lw
  parameter   SW      = 6'b101011;	// Opcode for sw
  parameter   RTYPE   = 6'b000000;	// Opcode for R-type
  parameter   BEQ     = 6'b000100;	// Opcode for beq
  parameter   ADDI    = 6'b001000;	// Opcode for addi
  parameter   J       = 6'b000010;	// Opcode for j

  reg [3:0]  state, nextstate;
  reg [14:0] controls;

  // state register
  always @(posedge clk or posedge reset)			
    if(reset) state <= FETCH;
    else state <= nextstate;

  // ADD CODE HERE
  // Finish entering the next state logic below.  We've completed the first 
  // two states, FETCH and DECODE, for you.

  // next state logic
  always @(*)
    case(state)
      FETCH:   nextstate <= DECODE;
      DECODE:  case(op)
                 LW:      nextstate <= MEMADR;
                 SW:      nextstate <= MEMADR;
                 RTYPE:   nextstate <= RTYPEEX;
                 BEQ:     nextstate <= BEQEX;
                 ADDI:    nextstate <= ADDIEX;
                 J:       nextstate <= JEX;
                 default: nextstate <= 4'bx; // should never happen
               endcase
 		// Add code here
      MEMADR:  case (op)
                LW:       nextstate <= MEMRD;
                SW:       nextstate <= MEMWR;
                default:  nextstate <= 4'bx; // should never happen
               endcase
      MEMRD:    nextstate <= MEMWB; 
      MEMWB:    nextstate <= FETCH;
      MEMWR:    nextstate <= FETCH;
      RTYPEEX:  nextstate <= RTYPEWB;
      RTYPEWB:  nextstate <= FETCH;
      BEQEX:    nextstate <= FETCH;
      ADDIEX:   nextstate <= ADDIWB;
      ADDIWB:   nextstate <= FETCH;
      JEX:      nextstate <= FETCH;
      default: nextstate <= 4'bx; // should never happen
    endcase

  // output logic
  assign {pcwrite, memwrite, irwrite, regwrite, 
          alusrca, branch, iord, memtoreg, regdst,
          alusrcb, pcsrc, aluop} = controls;

  // ADD CODE HERE
  // Finish entering the output logic below.  We've entered the
  // output logic for the first two states, S0 and S1, for you.
  always @(*)
    case(state)
      FETCH:   controls <= 15'h5010;
      DECODE:  controls <= 15'h0030;
      MEMADR:  controls <= 15'b000010000100000;
      MEMRD:   controls <= 15'b000000100000000;
      MEMWB:   controls <= 15'b000100010000000;
      MEMWR:   controls <= 15'b010000100000000;
      RTYPEEX: controls <= 15'b000010000000010; 
      RTYPEWB: controls <= 15'b000100001000000;
      BEQEX:   controls <= 15'b000011000000100;
      ADDIEX:  controls <= 15'b000010000100000;
      ADDIWB:  controls <= 15'b000100000000000;
      JEX:     controls <= 15'b100000000001000;
      default: controls <= 15'hxxxx; // should never happen
    endcase
endmodule

Multi Cycle/controler.v
module controller(input         clk, reset,
                  input   [5:0] op, funct,
                  input         zero,
                  output        pcen, memwrite, irwrite, regwrite,
                  output        alusrca, iord, memtoreg, regdst,
                  output  [1:0] alusrcb, pcsrc,
                  output  [3:0] alucontrol);

  wire [1:0] aluop;
  wire       branch, pcwrite;
  // Main Decoder and ALU Decoder subunits.
  maindec md(clk, reset, op,
             pcwrite, memwrite, irwrite, regwrite,
             alusrca, branch, iord, memtoreg, regdst, 
             alusrcb, pcsrc, aluop);
  aludec  ad(funct, aluop, alucontrol);

  assign pcen = (zero & branch) || pcwrite;
  
 
endmodule

Multi Cycle/controlertext_tb.v
module testbench();

  reg        clk;
  reg        reset;
  reg [5:0]  op, funct;
  reg        zero;
  wire       pcen, memwrite, irwrite, regwrite;
  wire       alusrca, iord, memtoreg, regdst;
  wire [1:0] alusrcb, pcsrc;
  wire [3:0] alucontrol;
  // instantiate device to be tested
  controller ctlr(clk, reset, op, funct, zero, pcen, memwrite, irwrite, regwrite, alusrca, iord, memtoreg, regdst, alusrcb, pcsrc, alucontrol);
  
  integer iter;

  // initialize test
  initial
    begin
      reset <= 1; # 10; reset <= 0;
      iter = 0;
    end

  
  reg [31:0] instrmem [0:17];

  initial
    begin
      $dumpfile("controller.vcd");
      $dumpvars;
      $readmemb("memfile.dat",instrmem);
    end

  // generate clock to sequence tests

  always begin
     #35 iter = iter+1;
  end
  
  always
    begin
      clk <= 1; # 5 clk = ~clk;
      {op, funct, zero } = instrmem[iter];
      $monitor("Clk:%h, reset:%h, op:%h, funct:%h, zero:%h, pcen:%h, memwrite:%h, irwrite:%h, regwrite:%h, alusrca:%h, iord:%h, memtoreg:%h, regdst:%h, alusrcb:%h, pcsrc:%h, aluop:%h, iter:%d", 
      clk, reset, op, funct, zero, pcen, memwrite, irwrite, regwrite, alusrca, iord, memtoreg, regdst, alusrcb, pcsrc, ctlr.aluop, iter); #5;
    end
endmodule

Multi Cycle/controller.vcd
$date
	Wed Jul 01 19:02:34 2020
$end
$version
	Icarus Verilog
$end
$timescale
	1s
$end
$scope module testbench $end
$var wire 1 ! regwrite $end
$var wire 1 " regdst $end
$var wire 2 # pcsrc [1:0] $end
$var wire 1 $ pcen $end
$var wire 1 % memwrite $end
$var wire 1 & memtoreg $end
$var wire 1 ' irwrite $end
$var wire 1 ( iord $end
$var wire 2 ) alusrcb [1:0] $end
$var wire 1 * alusrca $end
$var wire 4 + alucontrol [3:0] $end
$var reg 1 , clk $end
$var reg 6 - funct [5:0] $end
$var reg 6 . op [5:0] $end
$var reg 1 / reset $end
$var reg 1 0 zero $end
$var integer 32 1 iter [31:0] $end
$scope module ctlr $end
$var wire 1 , clk $end
$var wire 6 2 funct [5:0] $end
$var wire 6 3 op [5:0] $end
$var wire 1 $ pcen $end
$var wire 1 / reset $end
$var wire 1 0 zero $end
$var wire 1 ! regwrite $end
$var wire 1 " regdst $end
$var wire 1 4 pcwrite $end
$var wire 2 5 pcsrc [1:0] $end
$var wire 1 % memwrite $end
$var wire 1 & memtoreg $end
$var wire 1 ' irwrite $end
$var wire 1 ( iord $end
$var wire 1 6 branch $end
$var wire 2 7 alusrcb [1:0] $end
$var wire 1 * alusrca $end
$var wire 2 8 aluop [1:0] $end
$var wire 4 9 alucontrol [3:0] $end
$scope module ad $end
$var wire 6 : funct [5:0] $end
$var wire 2 ; aluop [1:0] $end
$var reg 4 < alucontrol [3:0] $end
$upscope $end
$scope module md $end
$var wire 1 , clk $end
$var wire 6 = op [5:0] $end
$var wire 1 / reset $end
$var wire 1 ! regwrite $end
$var wire 1 " regdst $end
$var wire 1 4 pcwrite $end
$var wire 2 > pcsrc [1:0] $end
$var wire 1 % memwrite $end
$var wire 1 & memtoreg $end
$var wire 1 ' irwrite $end
$var wire 1 ( iord $end
$var wire 1 6 branch $end
$var wire 2 ? alusrcb [1:0] $end
$var wire 1 * alusrca $end
$var wire 2 @ aluop [1:0] $end
$var reg 15 A controls [14:0] $end
$var reg 4 B nextstate [3:0] $end
$var reg 4 C state [3:0] $end
$upscope $end
$upscope $end
$upscope $end
$enddefinitions $end
#0
$dumpvars
b0 C
b1 B
b101000000010000 A
b0 @
b1 ?
b0 >
bx =
b0 <
b0 ;
bx :
b0 9
b0 8
b1 7
06
b0 5
14
bx 3
bx 2
bx 1
x0
1/
bx .
bx -
1,
b0 +
0*
b1 )
0(
1'
0&
0%
1$
b0 #
0"
0!
$end
#5
0,
#10
0$
04
0'
b11 )
b11 7
b11 ?
b110000 A
bx B
b1 C
1,
0/
b0 1
#15
b110 B
b0 .
b0 3
b0 =
b100000 -
b100000 2
b100000 :
00
0,
#20
1*
b0 )
b0 7
b0 ?
b10 8
b10 ;
b10 @
b10000000010 A
b111 B
b110 C
1,
#25
0,
#30
1!
0*
1"
b0 8
b0 ;
b0 @
b100001000000 A
b0 B
b111 C
1,
#35
b100010 -
b100010 2
b100010 :
0,
b1 1
#40
1$
14
1'
0!
0"
b1 )
b1 7
b1 ?
b101000000010000 A
b1 B
b0 C
1,
#45
0,
#50
0$
04
0'
b11 )
b11 7
b11 ?
b110000 A
b110 B
b1 C
1,
#55
0,
#60
b10 +
b10 9
b10 <
1*
b0 )
b0 7
b0 ?
b10 8
b10 ;
b10 @
b10000000010 A
b111 B
b110 C
1,
#65
0,
#70
b0 +
b0 9
b0 <
1!
0*
1"
b0 8
b0 ;
b0 @
b100001000000 A
b0 B
b111 C
1,
b10 1
#75
b100100 -
b100100 2
b100100 :
0,
#80
1$
14
1'
0!
0"
b1 )
b1 7
b1 ?
b101000000010000 A
b1 B
b0 C
1,
#85
0,
#90
0$
04
0'
b11 )
b11 7
b11 ?
b110000 A
b110 B
b1 C
1,
#95
0,
#100
b100 +
b100 9
b100 <
1*
b0 )
b0 7
b0 ?
b10 8
b10 ;
b10 @
b10000000010 A
b111 B
b110 C
1,
#105
b101 +
b101 9
b101 <
b100101 -
b100101 2
b100101 :
0,
b11 1
#110
b0 +
b0 9
b0 <
1!
0*
1"
b0 8
b0 ;
b0 @
b100001000000 A
b0 B
b111 C
1,
#115
0,
#120
1$
14
1'
0!
0"
b1 )
b1 7
b1 ?
b101000000010000 A
b1 B
b0 C
1,
#125
0,
#130
0$
04
0'
b11 )
b11 7
b11 ?
b110000 A
b110 B
b1 C
1,
#135
0,
#140
b101 +
b101 9
b101 <
1*
b0 )
b0 7
b0 ?
b10 8
b10 ;
b10 @
b10000000010 A
b111 B
b110 C
1,
b100 1
#145
b1010 +
b1010 9
b1010 <
b101010 -
b101010 2
b101010 :
0,
#150
b0 +
b0 9
b0 <
1!
0*
1"
b0 8
b0 ;
b0 @
b100001000000 A
b0 B
b111 C
1,
#155
0,
#160
1$
14
1'
0!
0"
b1 )
b1 7
b1 ?
b101000000010000 A
b1 B
b0 C
1,
#165
0,
#170
0$
04
0'
b11 )
b11 7
b11 ?
b110000 A
b110 B
b1 C
1,
#175
b10 B
b100011 .
b100011 3
b100011 =
bx -
bx 2
bx :
0,
b101 1
#180
1*
b10 )
b10 7
b10 ?
b10000100000 A
b11 B
b10 C
1,
#185
0,
#190
0*
1(
b0 )
b0 7
b0 ?
b100000000 A
b100 B
b11 C
1,
#195
0,
#200
1!
0(
1&
b100010000000 A
b0 B
b100 C
1,
#205
0,
#210
1$
14
1'
0!
0&
b1 )
b1 7
b1 ?
b101000000010000 A
b1 B
b0 C
1,
b110 1
#215
b101011 .
b101011 3
b101011 =
0,
#220
0$
04
0'
b11 )
b11 7
b11 ?
b110000 A
b10 B
b1 C
1,
#225
0,
#230
1*
b10 )
b10 7
b10 ?
b10000100000 A
b101 B
b10 C
1,
#235
0,
#240
1%
0*
1(
b0 )
b0 7
b0 ?
b10000100000000 A
b0 B
b101 C
1,
#245
b100 .
b100 3
b100 =
0,
b111 1
#250
1$
14
0%
1'
0(
b1 )
b1 7
b1 ?
b101000000010000 A
b1 B
b0 C
1,
#255
0,
#260
0$
04
0'
b11 )
b11 7
b11 ?
b110000 A
b1000 B
b1 C
1,
#265
0,
#270
1*
16
b0 )
b0 7
b0 ?
b1 #
b1 5
b1 >
b11000000100 A
b0 B
b1000 C
1,
#275
0,
#280
1$
14
1'
0*
06
b1 )
b1 7
b1 ?
b0 #
b0 5
b0 >
b101000000010000 A
b1 B
b0 C
1,
b1000 1
#285
b1000 .
b1000 3
b1000 =
0,
#290
0$
04
0'
b11 )
b11 7
b11 ?
b110000 A
b1001 B
b1 C
1,
#295
0,
#300
1*
b10 )
b10 7
b10 ?
b10000100000 A
b1010 B
b1001 C
1,
#305
0,
#310
1!
0*
b0 )
b0 7
b0 ?
b100000000000 A
b0 B
b1010 C
1,
#315
b10 .
b10 3
b10 =
0,
b1001 1
#320
1$
14
1'
0!
b1 )
b1 7
b1 ?
b101000000010000 A
b1 B
b0 C
1,
#325
0,
#330
0$
04
0'
b11 )
b11 7
b11 ?
b110000 A
b1011 B
b1 C
1,
#335
0,
#340
1$
14
b0 )
b0 7
b0 ?
b10 #
b10 5
b10 >
b100000000001000 A
b0 B
b1011 C
1,
#345
0,
#350
1'
b1 )
b1 7
b1 ?
b0 #
b0 5
b0 >
b101000000010000 A
b1 B
b0 C
1,
b1010 1
#355
b0 .
b0 3
b0 =
b100000 -
b100000 2
b100000 :
10
0,
#360
0$
04
0'
b11 )
b11 7
b11 ?
b110000 A
b110 B
b1 C
1,
#365
0,
#370
1*
b0 )
b0 7
b0 ?
b10 8
b10 ;
b10 @
b10000000010 A
b111 B
b110 C
1,
#375
0,
#380
1!
0*
1"
b0 8
b0 ;
b0 @
b100001000000 A
b0 B
b111 C
1,
#385
b100010 -
b100010 2
b100010 :
0,
b1011 1
#390
1$
14
1'
0!
0"
b1 )
b1 7
b1 ?
b101000000010000 A
b1 B
b0 C
1,
#395
0,
#400
0$
04
0'
b11 )
b11 7
b11 ?
b110000 A
b110 B
b1 C
1,
#405
0,
#410
b10 +
b10 9
b10 <
1*
b0 )
b0 7
b0 ?
b10 8
b10 ;
b10 @
b10000000010 A
b111 B
b110 C
1,
#415
0,
#420
b0 +
b0 9
b0 <
1!
0*
1"
b0 8
b0 ;
b0 @
b100001000000 A
b0 B
b111 C
1,
b1100 1
#425
b100100 -
b100100 2
b100100 :
0,
#430
1$
14
1'
0!
0"
b1 )
b1 7
b1 ?
b101000000010000 A
b1 B
b0 C
1,
#435
0,
#440
0$
04
0'
b11 )
b11 7
b11 ?
b110000 A
b110 B
b1 C
1,
#445
0,
#450
b100 +
b100 9
b100 <
1*
b0 )
b0 7
b0 ?
b10 8
b10 ;
b10 @
b10000000010 A
b111 B
b110 C
1,
#455
b101 +
b101 9
b101 <
b100101 -
b100101 2
b100101 :
0,
b1101 1
#460
b0 +
b0 9
b0 <
1!
0*
1"
b0 8
b0 ;
b0 @
b100001000000 A
b0 B
b111 C
1,
#465
0,
#470
1$
14
1'
0!
0"
b1 )
b1 7
b1 ?
b101000000010000 A
b1 B
b0 C
1,
#475
0,
#480
0$
04
0'
b11 )
b11 7
b11 ?
b110000 A
b110 B
b1 C
1,
#485
0,
#490
b101 +
b101 9
b101 <
1*
b0 )
b0 7
b0 ?
b10 8
b10 ;
b10 @
b10000000010 A
b111 B
b110 C
1,
b1110 1
#495
b1010 +
b1010 9
b1010 <
b101010 -
b101010 2
b101010 :
0,
#500
b0 +
b0 9
b0 <
1!
0*
1"
b0 8
b0 ;
b0 @
b100001000000 A
b0 B
b111 C
1,
#505
0,
#510
1$
14
1'
0!
0"
b1 )
b1 7
b1 ?
b101000000010000 A
b1 B
b0 C
1,
#515
0,
#520
0$
04
0'
b11 )
b11 7
b11 ?
b110000 A
b110 B
b1 C
1,
#525
b10 B
b100011 .
b100011 3
b100011 =
bx -
bx 2
bx :
0,
b1111 1
#530
1*
b10 )
b10 7
b10 ?
b10000100000 A
b11 B
b10 C
1,
#535
0,
#540
0*
1(
b0 )
b0 7
b0 ?
b100000000 A
b100 B
b11 C
1,
#545
0,
#550
1!
0(
1&
b100010000000 A
b0 B
b100 C
1,
#555
0,
#560
1$
14
1'
0!
0&
b1 )
b1 7
b1 ?
b101000000010000 A
b1 B
b0 C
1,
b10000 1
#565
b101011 .
b101011 3
b101011 =
0,
#570
0$
04
0'
b11 )
b11 7
b11 ?
b110000 A
b10 B
b1 C
1,
#575
0,
#580
1*
b10 )
b10 7
b10 ?
b10000100000 A
b101 B
b10 C
1,
#585
0,
#590
1%
0*
1(
b0 )
b0 7
b0 ?
b10000100000000 A
b0 B
b101 C
1,
#595
b100 .
b100 3
b100 =
0,
b10001 1
#600
1$
14
0%
1'
0(
b1 )
b1 7
b1 ?
b101000000010000 A
b1 B
b0 C
1,
#605
0,
#610
0$
04
0'
b11 )
b11 7
b11 ?
b110000 A
b1000 B
b1 C
1,
#615
0,
#620
1$
1*
16
b0 )
b0 7
b0 ?
b1 #
b1 5
b1 >
b11000000100 A
b0 B
b1000 C
1,
#625
0,
#630
14
1'
0*
06
b1 )
b1 7
b1 ?
b0 #
b0 5
b0 >
b101000000010000 A
b1 B
b0 C
1,
b10010 1
#635
bx .
bx 3
bx =
x0
0,
#640
0$
04
0'
b11 )
b11 7
b11 ?
b110000 A
bx B
b1 C
1,
#645
0,
#650
bx +
bx 9
bx <
x$
x4
x%
x'
x!
x*
x6
x(
x&
x"
bx )
bx 7
bx ?
bx #
bx 5
bx >
bx 8
bx ;
bx @
bx A
bx C
1,
#655
0,
#660
1,
#665
0,
b10011 1
#670
1,
#675
0,
#680
1,
#685
0,
#690
1,
#695
0,
#700
1,
b10100 1
#705
0,
#710
1,
#715
0,
#720
1,
#725
0,
#730
1,
#735
0,
b10101 1
#740
1,
#745
0,
#750
1,
#755
0,
#760
1,
#765
0,
#770
1,
b10110 1
#775
0,
#780
1,
#785
0,
#790
1,
#795
0,
#800
1,
#805
0,
b10111 1
#810
1,
#815
0,
#820
1,
#825
0,
#830
1,
#835
0,
#840
1,
b11000 1
#845
0,
#850
1,
#855
0,
#860
1,
#865
0,
#870
1,
#875
0,
b11001 1
#880
1,
#885
0,
#890
1,
#895
0,
#900
1,
#905
0,
#910
1,
b11010 1
#915
0,
#920
1,
#925
0,
#930
1,
#935
0,
#940
1,
#945
0,
b11011 1
#950
1,
#955
0,
#960
1,
#965
0,
#970
1,
#975
0,
#980
1,
b11100 1
#985
0,
#990
1,
#995
0,
#1000
1,
#1005
0,
#1010
1,
#1015
0,
b11101 1
#1020
1,
#1025
0,
#1030
1,
#1035
0,
#1040
1,
#1045
0,
#1050
1,
b11110 1
#1055
0,
#1060
1,
#1065
0,
#1070
1,
#1075
0,
#1080
1,
#1085
0,
b11111 1
#1090
1,
#1095
0,
#1100
1,
#1105
0,
#1110
1,
#1115
0,
#1120
1,
b100000 1
#1125
0,
#1130
1,
#1135
0,
#1140
1,
#1145
0,
#1150
1,
#1155
0,
b100001 1
#1160
1,
#1165
0,
#1170
1,
#1175
0,
#1180
1,
#1185
0,
#1190
1,
b100010 1
#1195
0,
#1200
1,
#1205
0,
#1210
1,
#1215
0,
#1220
1,
#1225
0,
b100011 1
#1230
1,
#1235
0,
#1240
1,
#1245
0,
#1250
1,
#1255
0,
#1260
1,
b100100 1
#1265
0,
#1270
1,
#1275
0,
#1280
1,
#1285
0,
#1290
1,
#1295
0,
b100101 1
#1300
1,
#1305
0,
#1310
1,
#1315
0,
#1320
1,
#1325
0,
#1330
1,
b100110 1
#1335
0,
#1340
1,
#1345
0,
#1350
1,
#1355
0,
#1360
1,
#1365
0,
b100111 1
#1370
1,
#1375
0,
#1380
1,
#1385
0,
#1390
1,
#1395
0,
#1400
1,
b101000 1
#1405
0,
#1410
1,
#1415
0,
#1420
1,
#1425
0,
#1430
1,
#1435
0,
b101001 1
#1440
1,
#1445
0,
#1450
1,
#1455
0,
#1460
1,
#1465
0,
#1470
1,
b101010 1
#1475
0,
#1480
1,
#1485
0,
#1490
1,
#1495
0,
#1500
1,
#1505
0,
b101011 1
#1510
1,
#1515
0,
#1520
1,
#1525
0,
#1530
1,
#1535
0,
#1540
1,
b101100 1
#1545
0,
#1550
1,
#1555
0,
#1560
1,
#1565
0,
#1570
1,
#1575
0,
b101101 1
#1580
1,
#1585
0,
#1590
1,
#1595
0,
#1600
1,
#1605
0,
#1610
1,
b101110 1
#1615
0,
#1620
1,
#1625
0,
#1630
1,
#1635
0,
#1640
1,
#1645
0,
b101111 1
#1650
1,
#1655
0,
#1660
1,
#1665
0,
#1670
1,
#1675
0,
#1680
1,
b110000 1
#1685
0,
#1690
1,
#1695
0,
#1700
1,
#1705
0,
#1710
1,
#1715
0,
b110001 1
#1720
1,
#1725
0,
#1730
1,
#1735
0,
#1740
1,
#1745
0,
#1750
1,
b110010 1
#1755
0,
#1760
1,
#1765
0,
#1770
1,
#1775
0,
#1780
1,
#1785
0,
b110011 1
#1790
1,
#1795
0,
#1800
1,
#1805
0,
#1810
1,
#1815
0,
#1820
1,
b110100 1
#1825
0,
#1830
1,
#1835
0,
#1840
1,
#1845
0,
#1850
1,
#1855
0,
b110101 1
#1860
1,
#1865
0,
#1870
1,
#1875
0,
#1880
1,
#1885
0,
#1890
1,
b110110 1
#1895
0,
#1900
1,
#1905
0,
#1910
1,
#1915
0,
#1920
1,
#1925
0,
b110111 1
#1930
1,
#1935
0,
#1940
1,
#1945
0,
#1950
1,
#1955
0,
#1960
1,
b111000 1
#1965
0,
#1970
1,
#1975
0,
#1980
1,
#1985
0,
#1990
1,
#1995
0,
b111001 1
#2000
1,
#2005
0,
#2010
1,
#2015
0,
#2020
1,
#2025
0,
#2030
1,
b111010 1
#2035
0,
#2040
1,
#2045
0,
#2050
1,
#2055
0,
#2060
1,
#2065
0,
b111011 1
#2070
1,
#2075
0,
#2080
1,
#2085
0,
#2090
1,
#2095
0,
#2100
1,
b111100 1
#2105
0,
#2110
1,
#2115
0,
#2120
1,
#2125
0,
#2130
1,
#2135
0,
b111101 1
#2140
1,
#2145
0,
#2150
1,
#2155
0,
#2160
1,
#2165
0,
#2170
1,
b111110 1
#2175
0,
#2180
1,
#2185
0,
#2190
1,
#2195
0,
#2200
1,
#2205
0,
b111111 1
#2210
1,
#2215
0,
#2220
1,
#2225
0,
#2230
1,
#2235
0,
#2240
1,
b1000000 1
#2245
0,
#2250
1,
#2255
0,
#2260
1,
#2265
0,
#2270
1,
#2275
0,
b1000001 1
#2280
1,
#2285
0,
#2290
1,
#2295
0,
#2300
1,
#2305
0,
#2310
1,
b1000010 1
#2315
0,
#2320
1,
#2325
0,
#2330
1,
#2335
0,
#2340
1,
#2345
0,
b1000011 1
#2350
1,
#2355
0,
#2360
1,
#2365
0,
#2370
1,
#2375
0,
#2380
1,
b1000100 1
#2385
0,
#2390
1,
#2395
0,
#2400
1,
#2405
0,
#2410
1,
#2415
0,
b1000101 1
#2420
1,
#2425
0,
#2430
1,
#2435
0,
#2440
1,
#2445
0,
#2450
1,
b1000110 1
#2455
0,
#2460
1,
#2465
0,
#2470
1,
#2475
0,
#2480
1,
#2485
0,
b1000111 1
#2490
1,
#2495
0,
#2500
1,
#2505
0,
#2510
1,
#2515
0,
#2520
1,
b1001000 1
#2525
0,
#2530
1,
#2535
0,
#2540
1,
#2545
0,
#2550
1,
#2555
0,
b1001001 1
#2560
1,
#2565
0,
#2570
1,
#2575
0,
#2580
1,
#2585
0,
#2590
1,
b1001010 1
#2595
0,
#2600
1,
#2605
0,
#2610
1,
#2615
0,
#2620
1,
#2625
0,
b1001011 1
#2630
1,
#2635
0,
#2640
1,
#2645
0,
#2650
1,
#2655
0,
#2660
1,
b1001100 1
#2665
0,
#2670
1,
#2675
0,
#2680
1,
#2685
0,
#2690
1,
#2695
0,
b1001101 1
#2700
1,
#2705
0,
#2710
1,
#2715
0,
#2720
1,
#2725
0,
#2730
1,
b1001110 1
#2735
0,
#2740
1,
#2745
0,
#2750
1,
#2755
0,
#2760
1,
#2765
0,
b1001111 1
#2770
1,
#2775
0,
#2780
1,
#2785
0,
#2790
1,
#2795
0,
#2800
1,
b1010000 1
#2805
0,
#2810
1,
#2815
0,
#2820
1,
#2825
0,
#2830
1,
#2835
0,
b1010001 1
#2840
1,
#2845
0,
#2850
1,
#2855
0,
#2860
1,
#2865
0,
#2870
1,
b1010010 1
#2875
0,
#2880
1,
#2885
0,
#2890
1,
#2895
0,
#2900
1,
#2905
0,
b1010011 1
#2910
1,
#2915
0,
#2920
1,
#2925
0,
#2930
1,
#2935
0,
#2940
1,
b1010100 1
#2945
0,
#2950
1,
#2955
0,
#2960
1,
#2965
0,
#2970
1,
#2975
0,
b1010101 1
#2980
1,
#2985
0,
#2990
1,
#2995
0,
#3000
1,
#3005
0,
#3010
1,
b1010110 1
#3015
0,
#3020
1,
#3025
0,
#3030
1,
#3035
0,
#3040
1,
#3045
0,
b1010111 1
#3050
1,
#3055
0,
#3060
1,
#3065
0,
#3070
1,
#3075
0,
#3080
1,
b1011000 1
#3085
0,
#3090
1,
#3095
0,
#3100
1,
#3105
0,
#3110
1,
#3115
0,
b1011001 1
#3120
1,
#3125
0,
#3130
1,
#3135
0,
#3140
1,
#3145
0,
#3150
1,
b1011010 1
#3155
0,
#3160
1,
#3165
0,
#3170
1,
#3175
0,
#3180
1,
#3185
0,
b1011011 1
#3190
1,
#3195
0,
#3200
1,
#3205
0,
#3210
1,
#3215
0,
#3220
1,
b1011100 1
#3225
0,
#3230
1,
#3235
0,
#3240
1,
#3245
0,
#3250
1,
#3255
0,
b1011101 1
#3260
1,
#3265
0,
#3270
1,
#3275
0,
#3280
1,
#3285
0,
#3290
1,
b1011110 1
#3295
0,
#3300
1,
#3305
0,
#3310
1,
#3315
0,
#3320
1,
#3325
0,
b1011111 1
#3330
1,
#3335
0,
#3340
1,
#3345
0,
#3350
1,
#3355
0,
#3360
1,
b1100000 1
#3365
0,
#3370
1,
#3375
0,
#3380
1,
#3385
0,
#3390
1,
#3395
0,
b1100001 1
#3400
1,
#3405
0,
#3410
1,
#3415
0,
#3420
1,
#3425
0,
#3430
1,
b1100010 1
#3435
0,
#3440
1,
#3445
0,
#3450
1,
#3455
0,
#3460
1,
#3465
0,
b1100011 1
#3470
1,
#3475
0,
#3480
1,
#3485
0,
#3490
1,
#3495
0,
#3500
1,
b1100100 1
#3505
0,
#3510
1,
#3515
0,
#3520
1,
#3525
0,
#3530
1,
#3535
0,
b1100101 1
#3540
1,
#3545
0,
#3550
1,
#3555
0,
#3560
1,
#3565
0,
#3570
1,
b1100110 1
#3575
0,
#3580
1,
#3585
0,
#3590
1,
#3595
0,
#3600
1,
#3605
0,
b1100111 1
#3610
1,
#3615
0,
#3620
1,
#3625
0,
#3630
1,
#3635
0,
#3640
1,
b1101000 1
#3645
0,
#3650
1,
#3655
0,
#3660
1,
#3665
0,
#3670
1,
#3675
0,
b1101001 1
#3680
1,
#3685
0,
#3690
1,
#3695
0,
#3700
1,
#3705
0,
#3710
1,
b1101010 1
#3715
0,
#3720
1,
#3725
0,
#3730
1,
#3735
0,
#3740
1,
#3745
0,
b1101011 1
#3750
1,
#3755
0,
#3760
1,
#3765
0,
#3770
1,
#3775
0,
#3780
1,
b1101100 1
#3785
0,
#3790
1,
#3795
0,
#3800
1,
#3805
0,
#3810
1,
#3815
0,
b1101101 1
#3820
1,
#3825
0,
#3830
1,
#3835
0,
#3840
1,
#3845
0,
#3850
1,
b1101110 1
#3855
0,
#3860
1,
#3865
0,
#3870
1,
#3875
0,
#3880
1,
#3885
0,
b1101111 1
#3890
1,
#3895
0,
#3900
1,
#3905
0,
#3910
1,
#3915
0,
#3920
1,
b1110000 1
#3925
0,
#3930
1,
#3935
0,
#3940
1,
#3945
0,
#3950
1,
#3955
0,
b1110001 1
#3960
1,
#3965
0,
#3970
1,
#3975
0,
#3980
1,
#3985
0,
#3990
1,
b1110010 1
#3995
0,
#4000
1,
#4005
0,
#4010
1,
#4015
0,
#4020
1,
#4025
0,
b1110011 1
#4030
1,
#4035
0,
#4040
1,
#4045
0,
#4050
1,
#4055
0,
#4060
1,
b1110100 1
#4065
0,
#4070
1,
#4075
0,
#4080
1,
#4085
0,
#4090
1,
#4095
0,
b1110101 1
#4100
1,
#4105
0,
#4110
1,
#4115
0,
#4120
1,
#4125
0,
#4130
1,
b1110110 1
#4135
0,
#4140
1,
#4145
0,
#4150
1,
#4155
0,
#4160
1,
#4165
0,
b1110111 1
#4170
1,
#4175
0,
#4180
1,
#4185
0,
#4190
1,
#4195
0,
#4200
1,
b1111000 1
#4205
0,
#4210
1,
#4215
0,
#4220
1,
#4225
0,
#4230
1,
#4235
0,
b1111001 1
#4240
1,
#4245
0,
#4250
1,
#4255
0,
#4260
1,
#4265
0,
#4270
1,
b1111010 1
#4275
0,
#4280
1,
#4285
0,
#4290
1,
#4295
0,
#4300
1,
#4305
0,
b1111011 1
#4310
1,
#4315
0,
#4320
1,
#4325
0,
#4330
1,
#4335
0,
#4340
1,
b1111100 1
#4345
0,
#4350
1,
#4355
0,
#4360
1,
#4365
0,
#4370
1,
#4375
0,
b1111101 1
#4380
1,
#4385
0,
#4390
1,
#4395
0,
#4400
1,
#4405
0,
#4410
1,
b1111110 1
#4415
0,
#4420
1,
#4425
0,
#4430
1,
#4435
0,
#4440
1,
#4445
0,
b1111111 1
#4450
1,
#4455
0,
#4460
1,
#4465
0,
#4470
1,
#4475
0,
#4480
1,
b10000000 1
#4485
0,
#4490
1,
#4495
0,
#4500
1,
#4505
0,
#4510
1,
#4515
0,
b10000001 1
#4520
1,
#4525
0,
#4530
1,
#4535
0,
#4540
1,
#4545
0,
#4550
1,
b10000010 1
#4555
0,
#4560
1,
#4565
0,
#4570
1,
#4575
0,
#4580
1,
