Multi Cycle/aludec.v

module aludec(input   [5:0] funct,
              input   [1:0] aluop,
              output  reg [3:0] alucontrol);

  always @ (*) begin
    case(aluop)
      2'b00: alucontrol <= 4'b0000;  // add
      2'b01: alucontrol <= 4'b0010;  // sub
      2'b11: alucontrol <= 4'b0101;  // or
      default: case(funct)          // RTYPE
          6'b100000: alucontrol <= 4'b0000; // ADD
          6'b100010: alucontrol <= 4'b0010; // SUB
          6'b100100: alucontrol <= 4'b0100; // AND
          6'b100101: alucontrol <= 4'b0101; // OR
          6'b100110: alucontrol <= 4'b0110; // XOR
          6'b100111: alucontrol <= 4'b0111; // NOR
          6'b101010: alucontrol <= 4'b1010; // SLT
          default:   alucontrol <= 4'bxxxx; // ???
        endcase
    endcase
  end
  // Remember that you may also reuse any code from previous labs.

endmodule

Multi Cycle/maindec.v

module maindec(input  logic       clk, reset, 
               input  logic [5:0] op, 
               output logic       pcwrite, memwrite, irwrite, regwrite,
               output logic       alusrca, branch, iord, memtoreg, regdst,
               output logic [1:0] alusrcb, pcsrc,
               output logic [1:0] aluop);

  parameter   FETCH   = 4'b0000; // State 0
  parameter   DECODE  = 4'b0001; // State 1
  parameter   MEMADR  = 4'b0010;	// State 2
  parameter   MEMRD   = 4'b0011;	// State 3
  parameter   MEMWB   = 4'b0100;	// State 4
  parameter   MEMWR   = 4'b0101;	// State 5
  parameter   RTYPEEX = 4'b0110;	// State 6
  parameter   RTYPEWB = 4'b0111;	// State 7
  parameter   BEQEX   = 4'b1000;	// State 8
  parameter   ADDIEX  = 4'b1001;	// State 9
  parameter   ADDIWB  = 4'b1010;	// state 10
  parameter   JEX     = 4'b1011;	// State 11

  parameter   LW      = 6'b100011;	// Opcode for lw
  parameter   SW      = 6'b101011;	// Opcode for sw
  parameter   RTYPE   = 6'b000000;	// Opcode for R-type
  parameter   BEQ     = 6'b000100;	// Opcode for beq
  parameter   ADDI    = 6'b001000;	// Opcode for addi
  parameter   J       = 6'b000010;	// Opcode for j

  logic [3:0]  state, nextstate;
  logic [14:0] controls;

  // state register
  always_ff @(posedge clk or posedge reset)			
    if(reset) state <= FETCH;
    else state <= nextstate;

  // ADD CODE HERE
  // Finish entering the next state logic below.  We've completed the first 
  // two states, FETCH and DECODE, for you.

  // next state logic
  always_comb
    case(state)
      FETCH:   nextstate <= DECODE;
      DECODE:  case(op)
                 LW:      nextstate <= MEMADR;
                 SW:      nextstate <= MEMADR;
                 RTYPE:   nextstate <= RTYPEEX;
                 BEQ:     nextstate <= BEQEX;
                 ADDI:    nextstate <= ADDIEX;
                 J:       nextstate <= JEX;
                 default: nextstate <= 4'bx; // should never happen
               endcase
 		// Add code here
      MEMADR:
      MEMRD: 
      MEMWB: 
      MEMWR: 
      RTYPEEX: 
      RTYPEWB: 
      BEQEX:   
      ADDIEX:  
      ADDIWB:  
      JEX:     
      default: nextstate <= 4'bx; // should never happen
    endcase

  // output logic
  assign {pcwrite, memwrite, irwrite, regwrite, 
          alusrca, branch, iord, memtoreg, regdst,
          alusrcb, pcsrc, aluop} = controls;

  // ADD CODE HERE
  // Finish entering the output logic below.  We've entered the
  // output logic for the first two states, S0 and S1, for you.
  always_comb
    case(state)
      FETCH:   controls <= 15'h5010;
      DECODE:  controls <= 15'h0030;
    // your code goes here      
    
	 
      default: controls <= 15'hxxxx; // should never happen
    endcase
endmodule

Multi Cycle/controler.v
module controller(input         clk, reset,
                  input   [5:0] op, funct,
                  input         zero,
                  output        pcen, memwrite, irwrite, regwrite,
                  output        alusrca, iord, memtoreg, regdst,
                  output  [1:0] alusrcb, pcsrc,
                  output  [3:0] alucontrol);

  wire [1:0] aluop;
  wire       branch, pcwrite;
  // Main Decoder and ALU Decoder subunits.
  maindec md(clk, reset, op,
             pcwrite, memwrite, irwrite, regwrite,
             alusrca, branch, iord, memtoreg, regdst, 
             alusrcb, pcsrc, aluop);
  aludec  ad(funct, aluop, alucontrol);

  pcen = (zero & branch) || pcwrite;
  
 
endmodule

Multi Cycle/controlertext_tb.v
module testbench();
  reg        clk;
  reg        reset;
  reg [5:0]  op, funct;
  reg        zero;
  wire       pcen, memwrite, irwrite, regwrite;
  wire       alusrca, iord, memtoreg, regdst;
  wire [1:0] alusrcb, pcsrc;
  wire [3:0] alucontrol;
  // instantiate device to be tested
  controller ctlr(clk, reset, op, funct, zero, pcen, memwrite, 
  irwrite, regwrite, alusrca, iord, memtoreg, regdst, alusrcb, 
  pcsrc, alucontrol);

  always
    begin
      $monitor("Clk: h, reset: h, op: %h, funct: %h, zero: %h, pcen: %h, memwrite: %h, irwrite: %h, regwrite: %h, alusrca: %h, iord: %h, memtoreg: %h, regdst: %h, alusrcb: %h, pcsrc: %h, alucontrol %h", 
      clk, reset, op, funct, zero, pcen, memwrite, irwrite, regwrite, 
      alusrca, iord, memtoreg, regdst, alusrcb, pcsrc, alucontrol);
      # 5 clk = ~clk;
    end
  // initialize test
  initial
    begin
      $dumpfile("controller.vcd");
      $dumpvars;
      clk <= 1; 
      reset <= 1; # 5; reset <= 0;
       #5;  {op, funct, zero} = 13'b0000001000000;  //add
       #30; {op, funct, zero} = 13'b0000001000100;  //sub
       #40; {op, funct, zero} = 13'b0000001001000;  //and
       #40; {op, funct, zero} = 13'b0000001001010;  //or
       #40; {op, funct, zero} = 13'b0000001010100;  //slt
       #40; {op, funct, zero} = 13'b100011xxxxxx0;  //lw
       #50; {op, funct, zero} = 13'b101011xxxxxx0;  //sw
       #40; {op, funct, zero} = 13'b000100xxxxxx0;  //beq
       #30; {op, funct, zero} = 13'b001000xxxxxx0;  //addi
       #40; {op, funct, zero} = 13'b000010xxxxxx0;  //j
       #30; {op, funct, zero} = 13'b0000001000001;
       #40; {op, funct, zero} = 13'b0000001000101;
       #40; {op, funct, zero} = 13'b0000001001001;
       #40; {op, funct, zero} = 13'b0000001001011;
       #40; {op, funct, zero} = 13'b0000001010101;
       #40; {op, funct, zero} = 13'b100011xxxxxx1;
       #50; {op, funct, zero} = 13'b101011xxxxxx1;
       #40; {op, funct, zero} = 13'b000100xxxxxx1;
       #30; {op, funct, zero} = 13'b001000xxxxxx1;
       #40; {op, funct, zero} = 13'b000010xxxxxx1;
       #35;
      $stop;
    end
endmodule

Multi Cycle/controller.vcd
$date
	Wed Jul 15 00:15:47 2020
$end
$version
	Icarus Verilog
$end
$timescale
	1s
$end
$scope module testbench $end
$var wire 1 ! regwrite $end
$var wire 1 " regdst $end
$var wire 2 # pcsrc [1:0] $end
$var wire 1 $ pcen $end
$var wire 1 % memwrite $end
$var wire 1 & memtoreg $end
$var wire 1 ' irwrite $end
$var wire 1 ( iord $end
$var wire 2 ) alusrcb [1:0] $end
$var wire 1 * alusrca $end
$var wire 4 + alucontrol [3:0] $end
$var reg 1 , clk $end
$var reg 6 - funct [5:0] $end
$var reg 6 . op [5:0] $end
$var reg 1 / reset $end
$var reg 1 0 zero $end
$scope module ctlr $end
$var wire 1 , clk $end
$var wire 6 1 funct [5:0] $end
$var wire 6 2 op [5:0] $end
$var wire 1 $ pcen $end
$var wire 1 / reset $end
$var wire 1 0 zero $end
$var wire 1 ! regwrite $end
$var wire 1 " regdst $end
$var wire 1 3 pcwrite $end
$var wire 2 4 pcsrc [1:0] $end
$var wire 1 % memwrite $end
$var wire 1 & memtoreg $end
$var wire 1 ' irwrite $end
$var wire 1 ( iord $end
$var wire 1 5 branch $end
$var wire 2 6 alusrcb [1:0] $end
$var wire 1 * alusrca $end
$var wire 2 7 aluop [1:0] $end
$var wire 4 8 alucontrol [3:0] $end
$scope module ad $end
$var wire 6 9 funct [5:0] $end
$var wire 2 : aluop [1:0] $end
$var reg 4 ; alucontrol [3:0] $end
$upscope $end
$scope module md $end
$var wire 1 , clk $end
$var wire 6 < op [5:0] $end
$var wire 1 / reset $end
$var wire 1 ! regwrite $end
$var wire 1 " regdst $end
$var wire 1 3 pcwrite $end
$var wire 2 = pcsrc [1:0] $end
$var wire 1 % memwrite $end
$var wire 1 & memtoreg $end
$var wire 1 ' irwrite $end
$var wire 1 ( iord $end
$var wire 1 5 branch $end
$var wire 2 > alusrcb [1:0] $end
$var wire 1 * alusrca $end
$var wire 2 ? aluop [1:0] $end
$var reg 15 @ controls [14:0] $end
$var reg 4 A nextstate [3:0] $end
$var reg 4 B state [3:0] $end
$upscope $end
$upscope $end
$upscope $end
$enddefinitions $end
#0
$dumpvars
b0 B
b1 A
b101000000010000 @
b0 ?
b1 >
b0 =
bx <
b0 ;
b0 :
bx 9
b0 8
b0 7
b1 6
05
b0 4
13
bx 2
bx 1
x0
1/
bx .
bx -
1,
b0 +
0*
b1 )
0(
1'
0&
0%
1$
b0 #
0"
0!
$end
#5
0/
0,
#10
0$
03
0'
b11 )
b11 6
b11 >
b110000 @
b110 A
b1 B
b0 .
b0 2
b0 <
b100000 -
b100000 1
b100000 9
00
1,
#15
0,
#20
1*
b0 )
b0 6
b0 >
b10 7
b10 :
b10 ?
b10000000010 @
b111 A
b110 B
1,
#25
0,
#30
1!
0*
1"
b0 7
b0 :
b0 ?
b100001000000 @
b0 A
b111 B
1,
#35
0,
#40
1$
13
1'
0!
0"
b1 )
b1 6
b1 >
b101000000010000 @
b1 A
b0 B
1,
b100010 -
b100010 1
b100010 9
#45
0,
#50
0$
03
0'
b11 )
b11 6
b11 >
b110000 @
b110 A
b1 B
1,
#55
0,
#60
b10 +
b10 8
b10 ;
1*
b0 )
b0 6
b0 >
b10 7
b10 :
b10 ?
b10000000010 @
b111 A
b110 B
1,
#65
0,
#70
b0 +
b0 8
b0 ;
1!
0*
1"
b0 7
b0 :
b0 ?
b100001000000 @
b0 A
b111 B
1,
#75
0,
#80
1$
13
1'
0!
0"
b1 )
b1 6
b1 >
b101000000010000 @
b1 A
b0 B
1,
b100100 -
b100100 1
b100100 9
#85
0,
#90
0$
03
0'
b11 )
b11 6
b11 >
b110000 @
b110 A
b1 B
1,
#95
0,
#100
b100 +
b100 8
b100 ;
1*
b0 )
b0 6
b0 >
b10 7
b10 :
b10 ?
b10000000010 @
b111 A
b110 B
1,
#105
0,
#110
b0 +
b0 8
b0 ;
1!
0*
1"
b0 7
b0 :
b0 ?
b100001000000 @
b0 A
b111 B
1,
#115
0,
#120
1$
13
1'
0!
0"
b1 )
b1 6
b1 >
b101000000010000 @
b1 A
b0 B
1,
b100101 -
b100101 1
b100101 9
#125
0,
#130
0$
03
0'
b11 )
b11 6
b11 >
b110000 @
b110 A
b1 B
1,
#135
0,
#140
b101 +
b101 8
b101 ;
1*
b0 )
b0 6
b0 >
b10 7
b10 :
b10 ?
b10000000010 @
b111 A
b110 B
1,
#145
0,
#150
b0 +
b0 8
b0 ;
1!
0*
1"
b0 7
b0 :
b0 ?
b100001000000 @
b0 A
b111 B
1,
#155
0,
#160
1$
13
1'
0!
0"
b1 )
b1 6
b1 >
b101000000010000 @
b1 A
b0 B
1,
b101010 -
b101010 1
b101010 9
#165
0,
#170
0$
03
0'
b11 )
b11 6
b11 >
b110000 @
b110 A
b1 B
1,
#175
0,
#180
b1010 +
b1010 8
b1010 ;
1*
b0 )
b0 6
b0 >
b10 7
b10 :
b10 ?
b10000000010 @
b111 A
b110 B
1,
#185
0,
#190
b0 +
b0 8
b0 ;
1!
0*
1"
b0 7
b0 :
b0 ?
b100001000000 @
b0 A
b111 B
1,
#195
0,
#200
1$
13
1'
0!
0"
b1 )
b1 6
b1 >
b101000000010000 @
b1 A
b0 B
1,
b100011 .
b100011 2
b100011 <
bx -
bx 1
bx 9
#205
0,
#210
0$
03
0'
b11 )
b11 6
b11 >
b110000 @
b10 A
b1 B
1,
#215
0,
#220
1*
b10 )
b10 6
b10 >
b10000100000 @
b11 A
b10 B
1,
#225
0,
#230
0*
1(
b0 )
b0 6
b0 >
b100000000 @
b100 A
b11 B
1,
#235
0,
#240
1!
0(
1&
b100010000000 @
b0 A
b100 B
1,
#245
0,
#250
1$
13
1'
0!
0&
b1 )
b1 6
b1 >
b101000000010000 @
b1 A
b0 B
1,
b101011 .
b101011 2
b101011 <
#255
0,
#260
0$
03
0'
b11 )
b11 6
b11 >
b110000 @
b10 A
b1 B
1,
#265
0,
#270
1*
b10 )
b10 6
b10 >
b10000100000 @
b101 A
b10 B
1,
#275
0,
#280
1%
0*
1(
b0 )
b0 6
b0 >
b10000100000000 @
b0 A
b101 B
1,
#285
0,
#290
1$
13
0%
1'
0(
b1 )
b1 6
b1 >
b101000000010000 @
b1 A
b0 B
1,
b100 .
b100 2
b100 <
#295
0,
#300
0$
03
0'
b11 )
b11 6
b11 >
b110000 @
b1000 A
b1 B
1,
#305
0,
#310
1*
15
b0 )
b0 6
b0 >
b1 #
b1 4
b1 =
b11000000100 @
b0 A
b1000 B
1,
#315
0,
#320
1$
13
1'
0*
05
b1 )
b1 6
b1 >
b0 #
b0 4
b0 =
b101000000010000 @
b1 A
b0 B
1,
b1000 .
b1000 2
b1000 <
#325
0,
#330
0$
03
0'
b11 )
b11 6
b11 >
b110000 @
b1001 A
b1 B
1,
#335
0,
#340
1*
b10 )
b10 6
b10 >
b10000100000 @
b1010 A
b1001 B
1,
#345
0,
#350
1!
0*
b0 )
b0 6
b0 >
b100000000000 @
b0 A
b1010 B
1,
#355
0,
#360
1$
13
1'
0!
b1 )
b1 6
b1 >
b101000000010000 @
b1 A
b0 B
1,
b10 .
b10 2
b10 <
#365
0,
#370
0$
03
0'
b11 )
b11 6
b11 >
b110000 @
b1011 A
b1 B
1,
#375
0,
#380
1$
13
b0 )
b0 6
b0 >
b10 #
b10 4
b10 =
b100000000001000 @
b0 A
b1011 B
1,
#385
0,
#390
1'
b1 )
b1 6
b1 >
b0 #
b0 4
b0 =
b101000000010000 @
b1 A
b0 B
1,
b0 .
b0 2
b0 <
b100000 -
b100000 1
b100000 9
10
#395
0,
#400
0$
03
0'
b11 )
b11 6
b11 >
b110000 @
b110 A
b1 B
1,
#405
0,
#410
1*
b0 )
b0 6
b0 >
b10 7
b10 :
b10 ?
b10000000010 @
b111 A
b110 B
1,
#415
0,
#420
1!
0*
1"
b0 7
b0 :
b0 ?
b100001000000 @
b0 A
b111 B
1,
#425
0,
#430
1$
13
1'
0!
0"
b1 )
b1 6
b1 >
b101000000010000 @
b1 A
b0 B
1,
b100010 -
b100010 1
b100010 9
#435
0,
#440
0$
03
0'
b11 )
b11 6
b11 >
b110000 @
b110 A
b1 B
1,
#445
0,
#450
b10 +
b10 8
b10 ;
1*
b0 )
b0 6
b0 >
b10 7
b10 :
b10 ?
b10000000010 @
b111 A
b110 B
1,
#455
0,
#460
b0 +
b0 8
b0 ;
1!
0*
1"
b0 7
b0 :
b0 ?
b100001000000 @
b0 A
b111 B
1,
#465
0,
#470
1$
13
1'
0!
0"
b1 )
b1 6
b1 >
b101000000010000 @
b1 A
b0 B
1,
b100100 -
b100100 1
b100100 9
#475
0,
#480
0$
03
0'
b11 )
b11 6
b11 >
b110000 @
b110 A
b1 B
1,
#485
0,
#490
b100 +
b100 8
b100 ;
1*
b0 )
b0 6
b0 >
b10 7
b10 :
b10 ?
b10000000010 @
b111 A
b110 B
1,
#495
0,
#500
b0 +
b0 8
b0 ;
1!
0*
1"
b0 7
b0 :
b0 ?
b100001000000 @
b0 A
b111 B
1,
#505
0,
#510
1$
13
1'
0!
0"
b1 )
b1 6
b1 >
b101000000010000 @
b1 A
b0 B
1,
b100101 -
b100101 1
b100101 9
#515
0,
#520
0$
03
0'
b11 )
b11 6
b11 >
b110000 @
b110 A
b1 B
1,
#525
0,
#530
b101 +
b101 8
b101 ;
1*
b0 )
b0 6
b0 >
b10 7
b10 :
b10 ?
b10000000010 @
b111 A
b110 B
1,
#535
0,
#540
b0 +
b0 8
b0 ;
1!
0*
1"
b0 7
b0 :
b0 ?
b100001000000 @
b0 A
b111 B
1,
#545
0,
#550
1$
13
1'
0!
0"
b1 )
b1 6
b1 >
b101000000010000 @
b1 A
b0 B
1,
b101010 -
b101010 1
b101010 9
#555
0,
#560
0$
03
0'
b11 )
b11 6
b11 >
b110000 @
b110 A
b1 B
1,
#565
0,
#570
b1010 +
b1010 8
b1010 ;
1*
b0 )
b0 6
b0 >
b10 7
b10 :
b10 ?
b10000000010 @
b111 A
b110 B
1,
#575
0,
#580
b0 +
b0 8
b0 ;
1!
0*
1"
b0 7
b0 :
b0 ?
b100001000000 @
b0 A
b111 B
1,
#585
0,
#590
1$
13
1'
0!
0"
b1 )
b1 6
b1 >
b101000000010000 @
b1 A
b0 B
1,
b100011 .
b100011 2
b100011 <
bx -
bx 1
bx 9
#595
0,
#600
0$
03
0'
b11 )
b11 6
b11 >
b110000 @
b10 A
b1 B
1,
#605
0,
#610
1*
b10 )
b10 6
b10 >
b10000100000 @
b11 A
b10 B
1,
#615
0,
#620
0*
1(
b0 )
b0 6
b0 >
b100000000 @
b100 A
b11 B
1,
#625
0,
#630
1!
0(
1&
b100010000000 @
b0 A
b100 B
1,
#635
0,
#640
1$
13
1'
0!
0&
b1 )
b1 6
b1 >
b101000000010000 @
b1 A
b0 B
1,
b101011 .
b101011 2
b101011 <
#645
0,
#650
0$
03
0'
b11 )
b11 6
b11 >
b110000 @
b10 A
b1 B
1,
#655
0,
#660
1*
b10 )
b10 6
b10 >
b10000100000 @
b101 A
b10 B
1,
#665
0,
#670
1%
0*
1(
b0 )
b0 6
b0 >
b10000100000000 @
b0 A
b101 B
1,
#675
0,
#680
1$
13
0%
1'
0(
b1 )
b1 6
b1 >
b101000000010000 @
b1 A
b0 B
1,
b100 .
b100 2
b100 <
#685
0,
#690
0$
03
0'
b11 )
b11 6
b11 >
b110000 @
b1000 A
b1 B
1,
#695
0,
#700
1$
1*
15
b0 )
b0 6
b0 >
b1 #
b1 4
b1 =
b11000000100 @
b0 A
b1000 B
1,
#705
0,
#710
13
1'
0*
05
b1 )
b1 6
b1 >
b0 #
b0 4
b0 =
b101000000010000 @
b1 A
b0 B
1,
b1000 .
b1000 2
b1000 <
#715
0,
#720
0$
03
0'
b11 )
b11 6
b11 >
b110000 @
b1001 A
b1 B
1,
#725
0,
#730
1*
b10 )
b10 6
b10 >
b10000100000 @
b1010 A
b1001 B
1,
#735
0,
#740
1!
0*
b0 )
b0 6
b0 >
b100000000000 @
b0 A
b1010 B
1,
#745
0,
#750
1$
13
1'
0!
b1 )
b1 6
b1 >
b101000000010000 @
b1 A
b0 B
1,
b10 .
b10 2
b10 <
#755
0,
#760
0$
03
0'
b11 )
b11 6
b11 >
b110000 @
b1011 A
b1 B
1,
#765
0,
#770
1$
13
b0 )
b0 6
b0 >
b10 #
b10 4
b10 =
b100000000001000 @
b0 A
b1011 B
1,
#775
0,
#780
1'
b1 )
b1 6
b1 >
b0 #
b0 4
b0 =
b101000000010000 @
b1 A
b0 B
1,
